scanscope/__init__.py
scanscope/__main__.py
scanscope/args.py
scanscope/data.py
scanscope/html.py
scanscope/log.py
scanscope/parser.py
scanscope/portmap.py
scanscope/sql.py
scanscope/utils.py
scanscope/writer.py
scanscope/static/bootstrap.bundle.min.js
scanscope/static/bootstrap.min.css
scanscope/static/diagram-aux.js
scanscope/static/gridjs.production.min.js
scanscope/static/mermaid.dark.css
scanscope/static/mermaid.min.css
scanscope/static/scanscope.css
scanscope/static/sql-aux.js
scanscope/static/sql-wasm.min.js
scanscope/static/sql-wasm.wasm
scanscope/static/utils.js
scanscope/templates/_test.html
scanscope/templates/base.html
scanscope/templates/diagram.html
scanscope/templates/hosts.html
scanscope/templates/html-templates.html
scanscope/templates/index.html
scanscope/templates/info.html
scanscope/templates/licenses.html
scanscope/templates/services.html
scanscope/templates/sidebar.html
scanscope-1.0.0.dist-info/METADATA
scanscope-1.0.0.dist-info/WHEEL
scanscope-1.0.0.dist-info/entry_points.txt
scanscope-1.0.0.dist-info/licenses/LICENSE
scanscope-1.0.0.dist-info/RECORD
