Metadata-Version: 2.4
Name: scanscope
Version: 1.0.0
Summary: Visualize portscan results
Author-email: Adrian Vollmer <adrian.vollmer@syss.de>
License: MIT License
License-File: LICENSE
Keywords: data-science,nmap,pentest,portscan,visualization
Classifier: Operating System :: POSIX :: Linux
Classifier: Programming Language :: Python
Classifier: Programming Language :: Python :: 3
Classifier: Programming Language :: Python :: 3.7
Classifier: Programming Language :: Python :: 3.8
Classifier: Programming Language :: Python :: 3.9
Classifier: Programming Language :: Python :: 3.10
Requires-Python: >=3.7
Requires-Dist: beautifulsoup4
Requires-Dist: bokeh>=3.2
Requires-Dist: joblib
Requires-Dist: lxml
Requires-Dist: numpy
Requires-Dist: pandas
Requires-Dist: python-libnmap
Requires-Dist: pyxdg
Requires-Dist: umap-learn
Requires-Dist: zundler
